.DS_Store
CHANGES.txt
LICENSE.txt
MANIFEST.in
PYREADME.md
README.md
setup.py
ss1.png
ss2.png
ss3.png
.idea/.name
.idea/encodings.xml
.idea/misc.xml
.idea/modules.xml
.idea/other.xml
.idea/pelican_admin.iml
.idea/testrunner.xml
.idea/vcs.xml
.idea/workspace.xml
.idea/inspectionProfiles/profiles_settings.xml
.idea/libraries/sass_stdlib.xml
.idea/scopes/scope_settings.xml
pelican_admin/.DS_Store
pelican_admin/__init__.py
pelican_admin/__init__.pyc
pelican_admin/helper.py
pelican_admin/models.pyc
pelican_admin/modules.py
pelican_admin/settings.pyc
pelican_admin/tests.py
pelican_admin/urls.py
pelican_admin/views.py
pelican_admin.egg-info/PKG-INFO
pelican_admin.egg-info/SOURCES.txt
pelican_admin.egg-info/dependency_links.txt
pelican_admin.egg-info/not-zip-safe
pelican_admin.egg-info/requires.txt
pelican_admin.egg-info/top_level.txt
pelican_admin/admin/__init__.py
pelican_admin/admin/__init__.pyc
pelican_admin/admin/blog_post_admin.py
pelican_admin/admin/blog_post_admin.pyc
pelican_admin/admin/category_admin.py
pelican_admin/admin/settings_admin.py
pelican_admin/admin/settings_admin.pyc
pelican_admin/locale/en_US/LC_MESSAGES/django.mo
pelican_admin/locale/en_US/LC_MESSAGES/django.po
pelican_admin/locale/en_US/LC_MESSAGES/djangojs.mo
pelican_admin/locale/en_US/LC_MESSAGES/djangojs.po
pelican_admin/locale/pt_BR/LC_MESSAGES/django.mo
pelican_admin/locale/pt_BR/LC_MESSAGES/django.po
pelican_admin/locale/pt_BR/LC_MESSAGES/djangojs.mo
pelican_admin/locale/pt_BR/LC_MESSAGES/djangojs.po
pelican_admin/migrations/0001_initial.py
pelican_admin/migrations/0002_auto__add_category__add_field_blogpost_category__add_field_blogpost_ta.py
pelican_admin/migrations/0003_auto__add_field_blogpost_status.py
pelican_admin/migrations/__init__.py
pelican_admin/models/__init__.py
pelican_admin/models/__init__.pyc
pelican_admin/models/blog_post.py
pelican_admin/models/blog_post.pyc
pelican_admin/models/category.py
pelican_admin/models/settings.py
pelican_admin/models/settings.pyc
pelican_admin/static/pelican_admin/loading.gif
pelican_admin/static/pelican_admin/main.js
pelican_admin/templates/pelican_admin.html
pelican_admin/templates/admin/pelican_admin/blogpost/change_form.html