Metadata-Version: 1.0
Name: pelican-admin
Version: 0.3
Summary: Django admin app for Pelican blogs.
Home-page: https://github.com/fjcaetano/pelican_admin
Author: Flávio Caetano
Author-email: flavio@vieiracaetano.com
License: GPL - see LICENSE.txt
Platform: any
Classifier: Environment :: Web Environment
Classifier: Framework :: Django
Classifier: Development Status :: 4 - Beta
Classifier: License :: OSI Approved :: GNU General Public License (GPL)
Classifier: Topic :: Internet :: WWW/HTTP :: Dynamic Content
